plexwebsocket.py
plexwebsocket-0.0.14.dist-info/LICENSE
plexwebsocket-0.0.14.dist-info/METADATA
plexwebsocket-0.0.14.dist-info/WHEEL
plexwebsocket-0.0.14.dist-info/top_level.txt
plexwebsocket-0.0.14.dist-info/RECORD
