Metadata-Version: 2.1
Name: plexwebsocket
Version: 0.0.14
Summary: Support for issuing callbacks in response to Plex websocket updates.
Home-page: https://github.com/jjlawren/python-plexwebsocket/
Author: Jason Lawrence
Author-email: jjlawren@users.noreply.github.com
License: MIT
Platform: any
Classifier: License :: OSI Approved :: MIT License
Classifier: Operating System :: OS Independent
Classifier: Programming Language :: Python :: 3.6
Classifier: Programming Language :: Python :: 3.7
Classifier: Programming Language :: Python :: 3.8
